god_mcp/__init__.py
god_mcp/config_manager.py
god_mcp/models.py
god_mcp/server.py
god_mcp/server_creator.py
god_mcp/templates/README.md.template
god_mcp/templates/__init__.py
god_mcp/templates/logging_config.py.template
god_mcp/templates/pyproject.toml.template
god_mcp/templates/server.py.template
god_mcp-0.1.0.dist-info/METADATA
god_mcp-0.1.0.dist-info/WHEEL
god_mcp-0.1.0.dist-info/entry_points.txt
god_mcp-0.1.0.dist-info/licenses/LICENSE
god_mcp-0.1.0.dist-info/RECORD
